gioconda/__init__.py
gioconda/_data.py
gioconda/_file.py
gioconda/_matrix.py
gioconda/_methods.py
gioconda/test_data.csv
gioconda-1.6.0.dist-info/LICENSE
gioconda-1.6.0.dist-info/METADATA
gioconda-1.6.0.dist-info/WHEEL
gioconda-1.6.0.dist-info/top_level.txt
gioconda-1.6.0.dist-info/RECORD
