Metadata-Version: 2.1
Name: gioconda
Version: 1.6.0
Summary: handles tabular data
Home-page: https://github.com/piccolomo/gioconda
Author: Savino Piccolomo
Author-email: piccolomo@gmail.com
License: MIT
Platform: UNKNOWN
Requires-Python: >=3.10.0, <=3.11.4
License-File: LICENSE
Requires-Dist: matplotlib (>=3.7.0)
Requires-Dist: numpy (>=1.24.0)
